buildfile/__init__.py
buildfile/__main__.py
buildfile/buildfile.py
buildfile-1.1.1.dist-info/LICENSE
buildfile-1.1.1.dist-info/METADATA
buildfile-1.1.1.dist-info/WHEEL
buildfile-1.1.1.dist-info/top_level.txt
buildfile-1.1.1.dist-info/RECORD
