Metadata-Version: 2.1
Name: buildfile
Version: 1.1.1
Summary: Renamed to cmdfile
Author-email: Stuntlover <stuntlover@aluvia.de>
Project-URL: Homepage, https://github.com/Stuntlover-TM/cmdfile
Project-URL: Bug Tracker, https://github.com/Stuntlover-TM/cmdfile/issues
Classifier: Programming Language :: Python :: 3
Classifier: License :: OSI Approved :: MIT License
Classifier: Operating System :: OS Independent
Requires-Python: >=3.9
License-File: LICENSE
